README.rst
setup.py
kombu_django/__init__.py
kombu_django/serializer.py
kombu_django_json_serializer.egg-info/PKG-INFO
kombu_django_json_serializer.egg-info/SOURCES.txt
kombu_django_json_serializer.egg-info/dependency_links.txt
kombu_django_json_serializer.egg-info/entry_points.txt
kombu_django_json_serializer.egg-info/top_level.txt