Metadata-Version: 1.1
Name: kombu-django-json-serializer
Version: 0.1.0
Summary: A JSON serializer for Kombu that makes use of Django's extended JSON serializers
Home-page: https://github.com/anentropic/kombu-django-json-serializer
Author: Anentropic
Author-email: ego@anentropic.com
License: MIT
Platform: UNKNOWN
Classifier: Environment :: Web Environment
Classifier: Intended Audience :: Developers
Classifier: License :: OSI Approved :: MIT License
Classifier: Operating System :: OS Independent
Classifier: Programming Language :: Python
Classifier: Framework :: Django
